kitsu/__init__.py
kitsu/logger.py
kitsu/loss.py
kitsu/main.py
kitsu/options.py
kitsu/sched.py
kitsu/trainer.py
kitsu/metrics/__init__.py
kitsu/metrics/pointcloud.py
kitsu/module/__init__.py
kitsu/module/func.py
kitsu/module/geglu.py
kitsu/module/init.py
kitsu/module/seqlen_utils.py
kitsu/module/transformer.py
kitsu/module/loss/__init__.py
kitsu/module/loss/focal.py
kitsu/module/loss/utils.py
kitsu/utils/__init__.py
kitsu/utils/data.py
kitsu/utils/dist.py
kitsu/utils/ema.py
kitsu/utils/indexing.py
kitsu/utils/interp1d.py
kitsu/utils/io.py
kitsu/utils/optim.py
kitsu/utils/plot.py
kitsu/utils/system.py
kitsu/utils/threading.py
kitsu/utils/utils.py
kitsu/utils/vis3d.py
kitsu/utils/vis_text.py
kitsu-0.1.2.7.dist-info/LICENSE
kitsu-0.1.2.7.dist-info/METADATA
kitsu-0.1.2.7.dist-info/WHEEL
kitsu-0.1.2.7.dist-info/top_level.txt
kitsu-0.1.2.7.dist-info/RECORD
