Metadata-Version: 2.1
Name: kitsu
Version: 0.1.2.7
Summary: UNKNOWN
Home-page: https://github.com/Kitsunetic/kitsu
Author: Kitsunetic
Author-email: jh.shim.gg@gmail.com
License: UNKNOWN
Platform: UNKNOWN
License-File: LICENSE
Requires-Dist: scikit-image
Requires-Dist: omegaconf
Requires-Dist: easydict
Requires-Dist: tqdm
Requires-Dist: matplotlib
